LICENSE
README.md
setup.py
MorphologicalDisambiguation/AutoDisambiguator.c
MorphologicalDisambiguation/AutoDisambiguator.pxd
MorphologicalDisambiguation/AutoDisambiguator.pyx
MorphologicalDisambiguation/DummyDisambiguation.c
MorphologicalDisambiguation/DummyDisambiguation.pyx
MorphologicalDisambiguation/HmmDisambiguation.c
MorphologicalDisambiguation/HmmDisambiguation.pyx
MorphologicalDisambiguation/LongestRootFirstDisambiguation.c
MorphologicalDisambiguation/LongestRootFirstDisambiguation.pyx
MorphologicalDisambiguation/MorphologicalDisambiguator.c
MorphologicalDisambiguation/MorphologicalDisambiguator.pxd
MorphologicalDisambiguation/MorphologicalDisambiguator.pyx
MorphologicalDisambiguation/NaiveDisambiguation.c
MorphologicalDisambiguation/NaiveDisambiguation.pxd
MorphologicalDisambiguation/NaiveDisambiguation.pyx
MorphologicalDisambiguation/RootFirstDisambiguation.c
MorphologicalDisambiguation/RootFirstDisambiguation.pyx
MorphologicalDisambiguation/__init__.py
MorphologicalDisambiguation/data/__init__.py
MorphologicalDisambiguation/data/rootlist.txt
NlpToolkit_MorphologicalDisambiguation_Cy.egg-info/PKG-INFO
NlpToolkit_MorphologicalDisambiguation_Cy.egg-info/SOURCES.txt
NlpToolkit_MorphologicalDisambiguation_Cy.egg-info/dependency_links.txt
NlpToolkit_MorphologicalDisambiguation_Cy.egg-info/requires.txt
NlpToolkit_MorphologicalDisambiguation_Cy.egg-info/top_level.txt
nlptoolkit_morphologicaldisambiguation_cy.egg-info/PKG-INFO
nlptoolkit_morphologicaldisambiguation_cy.egg-info/SOURCES.txt
nlptoolkit_morphologicaldisambiguation_cy.egg-info/dependency_links.txt
nlptoolkit_morphologicaldisambiguation_cy.egg-info/requires.txt
nlptoolkit_morphologicaldisambiguation_cy.egg-info/top_level.txt