Metadata-Version: 2.1
Name: nlptoolkit-morphologicaldisambiguation-cy
Version: 1.0.13
Summary: Turkish Morphological Disambiguation Library
Home-page: https://github.com/StarlangSoftware/TurkishMorphologicalDisambiguation-Cy
Author: olcaytaner
Author-email: olcay.yildiz@ozyegin.edu.tr
License: UNKNOWN
Platform: UNKNOWN
